declient/__init__.py
declient/decompile.py
declient/decompile_async.py
pydeclient-1.1.0.dist-info/LICENSE
pydeclient-1.1.0.dist-info/METADATA
pydeclient-1.1.0.dist-info/WHEEL
pydeclient-1.1.0.dist-info/top_level.txt
pydeclient-1.1.0.dist-info/RECORD
