Metadata-Version: 2.1
Name: pydeclient
Version: 1.1.0
Summary: A package for requesting decompilebench service
Author: hustcw
License: MIT
Keywords: decompiler,binary,reverse engineering
Classifier: Programming Language :: Python :: 3
Classifier: License :: OSI Approved :: MIT License
Classifier: Operating System :: OS Independent
License-File: LICENSE
Requires-Dist: aiohttp
Requires-Dist: requests
Requires-Dist: tqdm
